{"data":{"propertyOrder":{},"properties":{},"props":[],"primaryKeys":[],"filters":{},"hooks":{},"indexes":[],"uniques":[],"checks":[],"concurrencyCheckKeys":{},"className":"Ingridient","path":"./dist/entities/Ingridient.entity.js","name":"Ingridient","abstract":false,"constructorParams":[],"toJsonParams":[],"extends":"CustomBaseEntity","useCache":true,"relations":[],"collection":"ingridient"},"origin":"./dist/entities/Ingridient.entity.js","hash":"b14eb9f709175bf27eaf77790125f330","version":"5.6.16"}
